aliyun_log_py_bindings-0.0.5.dist-info/METADATA
aliyun_log_py_bindings-0.0.5.dist-info/WHEEL
aliyun_log_py_bindings-0.0.5.dist-info/licenses/LICENSE
aliyun_log_py_bindings/__init__.py
aliyun_log_py_bindings/aliyun_log_py_bindings.pyi
aliyun_log_py_bindings/log_parser/__init__.py
aliyun_log_py_bindings/log_parser/__init__.pyi
aliyun_log_py_bindings/__init__.pyi
aliyun_log_py_bindings/py.typed
aliyun_log_py_bindings/aliyun_log_py_bindings.pypy310-pp73-arm-linux-gnu.so
aliyun_log_py_bindings-0.0.5.dist-info/RECORD
