Metadata-Version: 2.4
Name: aliyun-log-py-bindings
Version: 0.0.5
Classifier: Programming Language :: Python :: 3
Classifier: Programming Language :: Python :: 3.7
Classifier: Programming Language :: Python :: 3.8
Classifier: Programming Language :: Python :: 3.9
Classifier: Programming Language :: Python :: 3.10
Classifier: Programming Language :: Python :: 3.11
Classifier: Programming Language :: Python :: 3.12
Classifier: Programming Language :: Python :: Implementation :: CPython
Classifier: Programming Language :: Python :: Implementation :: PyPy
Classifier: Programming Language :: Rust
Requires-Dist: pytest ; extra == 'dev'
Requires-Dist: pytest-benchmark[histogram] ; extra == 'dev'
Provides-Extra: dev
License-File: LICENSE
Summary: Py bindings for aliyun log service sdk
Keywords: aliyun,sls,pyo3
Author: crimson
License: MIT
Requires-Python: >=3.7
